LICENSE
README.md
setup.py
cryoCARE_mpido.egg-info/PKG-INFO
cryoCARE_mpido.egg-info/SOURCES.txt
cryoCARE_mpido.egg-info/dependency_links.txt
cryoCARE_mpido.egg-info/requires.txt
cryoCARE_mpido.egg-info/top_level.txt
cryocare/__init__.py
cryocare/internals/CryoCARE.py
cryocare/internals/CryoCAREDataModule.py
cryocare/internals/__init__.py
cryocare/scripts/__init__.py
cryocare/scripts/cryoCARE_extract_train_data.py
cryocare/scripts/cryoCARE_predict.py
cryocare/scripts/cryoCARE_train.py