Metadata-Version: 2.1
Name: cryoCARE-mpido
Version: 0.2.2
Summary: cryoCARE is a deep learning approach for cryo-TEM tomogram denoising.
Home-page: https://github.com/thorstenwagner/cryoCARE_pip
Author: Thorsten Wagner
Author-email: thorsten.wagner@mpi-dortmund.mpg.de
Classifier: Programming Language :: Python :: 3
Classifier: Development Status :: 4 - Beta
Classifier: Intended Audience :: Science/Research
Classifier: Topic :: Scientific/Engineering
Classifier: License :: OSI Approved :: BSD License
Requires-Python: >=3.6
Provides-Extra: c11
License-File: LICENSE
